autofex/__init__.py
autofex/cli.py
autofex/core.py
autofex/analysis/__init__.py
autofex/analysis/statistical.py
autofex/analysis/ultra_stats.py
autofex/benchmarking/__init__.py
autofex/benchmarking/benchmarker.py
autofex/data_profiling/__init__.py
autofex/data_profiling/profiler.py
autofex/feature_engineering/__init__.py
autofex/feature_engineering/advanced.py
autofex/feature_engineering/engineer.py
autofex/feature_selection/__init__.py
autofex/feature_selection/selector.py
autofex/intelligence/__init__.py
autofex/intelligence/orchestrator.py
autofex/intelligence/quality_scorer.py
autofex/intelligence/recommender.py
autofex/leakage_detection/__init__.py
autofex/leakage_detection/detector.py
autofex/lineage/__init__.py
autofex/lineage/tracker.py
autofex/mathematical/__init__.py
autofex/mathematical/modeling.py
autofex/numpy/__init__.py
autofex/numpy/operations.py
autofex/pandas/__init__.py
autofex/pandas/operations.py
autofex/pandas_advanced/operations.py
autofex/scipy/__init__.py
autofex/scipy/operations.py
autofex/statistical/__init__.py
autofex/statistical/stat_transforms.py
autofex/utils/__init__.py
autofex/utils/cache.py
autofex/utils/helpers.py
autofex/utils/parallel.py
autofex/utils/progress.py
autofex/visualization/__init__.py
autofex/visualization/dashboard.py
autofex/visualization/multidimensional.py
autofex/visualization/plotter.py
autofex-0.1.6.dist-info/licenses/LICENSE
autofex-0.1.6.dist-info/METADATA
autofex-0.1.6.dist-info/WHEEL
autofex-0.1.6.dist-info/entry_points.txt
autofex-0.1.6.dist-info/top_level.txt
autofex-0.1.6.dist-info/RECORD
