Metadata-Version: 2.4
Name: autofex
Version: 0.1.6
Summary: A unified toolkit for automated feature engineering, data diagnostics, leakage detection, benchmarking, and feature lineage for modern ML workflows
Home-page: https://github.com/sudo-de/autofex
Author: AutoFE-X
Author-email: AutoFE-X Team <sudo.dev26@gmail.com>
License: MIT
Project-URL: Homepage, https://github.com/sudo-de/autofe-x
Project-URL: Documentation, https://github.com/sudo-de/autofe-x#readme
Project-URL: Repository, https://github.com/sudo-de/autofe-x
Project-URL: Issues, https://github.com/sudo-de/autofe-x/issues
Project-URL: Discussions, https://github.com/sudo-de/autofe-x/discussions
Keywords: machine-learning,feature-engineering,data-profiling,leakage-detection,automl,data-science
Classifier: Development Status :: 3 - Alpha
Classifier: Intended Audience :: Developers
Classifier: Intended Audience :: Science/Research
Classifier: License :: OSI Approved :: MIT License
Classifier: Operating System :: OS Independent
Classifier: Programming Language :: Python :: 3
Classifier: Programming Language :: Python :: 3.8
Classifier: Programming Language :: Python :: 3.9
Classifier: Programming Language :: Python :: 3.10
Classifier: Programming Language :: Python :: 3.11
Classifier: Programming Language :: Python :: 3.12
Classifier: Programming Language :: Python :: 3.13
Classifier: Topic :: Scientific/Engineering :: Artificial Intelligence
Classifier: Topic :: Software Development :: Libraries :: Python Modules
Requires-Python: >=3.8,<3.14
License-File: LICENSE
Requires-Dist: pandas<2.3.0,>=1.3.0
Requires-Dist: numpy<2.1.0,>=1.20.0
Requires-Dist: scikit-learn>=1.0.0
Requires-Dist: scipy>=1.7.0
Requires-Dist: networkx>=2.6.0
Provides-Extra: dev
Requires-Dist: pytest>=6.0.0; extra == "dev"
Requires-Dist: pytest-cov>=2.0.0; extra == "dev"
Requires-Dist: black>=21.0.0; extra == "dev"
Requires-Dist: flake8>=3.9.0; extra == "dev"
Requires-Dist: mypy>=0.800; extra == "dev"
Requires-Dist: sphinx>=4.0.0; extra == "dev"
Requires-Dist: jupyter>=1.0.0; extra == "dev"
Requires-Dist: codecov>=2.1.0; extra == "dev"
Provides-Extra: viz
Requires-Dist: matplotlib>=3.4.0; extra == "viz"
Requires-Dist: seaborn>=0.11.0; extra == "viz"
Requires-Dist: plotly>=5.0.0; extra == "viz"
Requires-Dist: graphviz>=0.17.0; extra == "viz"
Provides-Extra: test
Requires-Dist: pytest>=6.0.0; extra == "test"
Requires-Dist: pytest-cov>=2.0.0; extra == "test"
Dynamic: author
Dynamic: home-page
Dynamic: license-file
Dynamic: requires-python
